beetsplug/beetrhythm/__init__.py
beetsplug/beetrhythm/plugin.py
beetrhythm-0.1.3.dist-info/LICENSE
beetrhythm-0.1.3.dist-info/METADATA
beetrhythm-0.1.3.dist-info/WHEEL
beetrhythm-0.1.3.dist-info/entry_points.txt
beetrhythm-0.1.3.dist-info/RECORD
