Metadata-Version: 2.3
Name: beetrhythm
Version: 0.1.3
Summary: A beets plugin for the deeprhythm tempo predictor
License: MIT
Keywords: beets,plugin,tempo,bpm,music,deeprhythm,ai
Author: bleugreen
Author-email: bleugreendesign@gmail.com
Requires-Python: >=3.8,<4.0
Classifier: Development Status :: 4 - Beta
Classifier: Intended Audience :: End Users/Desktop
Classifier: License :: OSI Approved :: MIT License
Classifier: Programming Language :: Python :: 3
Classifier: Programming Language :: Python :: 3.8
Classifier: Programming Language :: Python :: 3.9
Classifier: Programming Language :: Python :: 3.10
Classifier: Programming Language :: Python :: 3.11
Classifier: Programming Language :: Python :: 3.12
Classifier: Programming Language :: Python :: 3.13
Classifier: Topic :: Multimedia :: Sound/Audio
Classifier: Topic :: Software Development :: Libraries :: Python Modules
Requires-Dist: beets (>=2.0.0,<3.0.0)
Requires-Dist: deeprhythm (>=0.0.13,<0.0.14)
Project-URL: Homepage, https://github.com/bleugreen/deeprhythm-beets
Project-URL: Repository, https://github.com/bleugreen/deeprhythm-beets
